LICENSE
README.rst
setup.py
easy_audit_farrux.egg-info/PKG-INFO
easy_audit_farrux.egg-info/SOURCES.txt
easy_audit_farrux.egg-info/dependency_links.txt
easy_audit_farrux.egg-info/requires.txt
easy_audit_farrux.egg-info/top_level.txt
easyauditfarrux/__init__.py
easyauditfarrux/admin.py
easyauditfarrux/admin_helpers.py
easyauditfarrux/apps.py
easyauditfarrux/backends.py
easyauditfarrux/models.py
easyauditfarrux/settings.py
easyauditfarrux/tests.py
easyauditfarrux/utils.py
easyauditfarrux/views.py